setup.py
pikav1/__init__.py
pikav1/amqp_object.py
pikav1/callback.py
pikav1/channel.py
pikav1/compat.py
pikav1/connection.py
pikav1/credentials.py
pikav1/data.py
pikav1/diagnostic_utils.py
pikav1/exceptions.py
pikav1/frame.py
pikav1/heartbeat.py
pikav1/spec.py
pikav1/tcp_socket_opts.py
pikav1/validators.py
pikav1.egg-info/PKG-INFO
pikav1.egg-info/SOURCES.txt
pikav1.egg-info/dependency_links.txt
pikav1.egg-info/requires.txt
pikav1.egg-info/top_level.txt
pikav1/adapters/__init__.py
pikav1/adapters/asyncio_connection.py
pikav1/adapters/base_connection.py
pikav1/adapters/blocking_connection.py
pikav1/adapters/select_connection.py
pikav1/adapters/tornado_connection.py
pikav1/adapters/twisted_connection.py
pikav1/adapters/utils/__init__.py
pikav1/adapters/utils/connection_workflow.py
pikav1/adapters/utils/io_services_utils.py
pikav1/adapters/utils/nbio_interface.py
pikav1/adapters/utils/selector_ioloop_adapter.py